LICENSE
MANIFEST.in
README.rst
setup.py
config/auth.example.cfg
config/labels.example.cfg
filabel/__init__.py
filabel/__main__.py
filabel/cli.py
filabel/logic.py
filabel/utils.py
filabel/web.py
filabel/static/style.css
filabel/templates/infopage.html
filabel/templates/layout.html
filabel_cvut.egg-info/PKG-INFO
filabel_cvut.egg-info/SOURCES.txt
filabel_cvut.egg-info/dependency_links.txt
filabel_cvut.egg-info/entry_points.txt
filabel_cvut.egg-info/not-zip-safe
filabel_cvut.egg-info/requires.txt
filabel_cvut.egg-info/top_level.txt
test/test_behavior.py
test/test_errors.py
test/test_help.py
test/test_radioactive_waste.py
test/test_web_smoke.py